zefactor/api/finder/__init__.py
zefactor/api/finder/find_scanner.py
zefactor/api/finder/finder_refactor.py
zefactor/api/finder/finder_scan_manager.py
zefactor/api/finder/match_result.py
zefactor/api/replacer/__init__.py
zefactor/api/replacer/replacer.py
zefactor/api/replacer/replacer_manager.py
zefactor/api/transform/__init__.py
zefactor/api/transform/transform.py
zefactor/api/transform/transform_manager.py
zefactor/input/__init__.py
zefactor/input/loader.py
zefactor/input/prompt/__init__.py
zefactor/input/prompt/prompt_helper.py
zefactor/input/prompt/prompt_runner.py
zefactor/run/__init__.py
zefactor/run/auto_runner.py
zefactor/run/entries.py
zefactor/run/loader.py
zefactor/run/runner.py
zefactor/run/runner_manager.py
zefactor-2.0.0.dist-info/LICENSE
zefactor-2.0.0.dist-info/METADATA
zefactor-2.0.0.dist-info/WHEEL
zefactor-2.0.0.dist-info/entry_points.txt
zefactor-2.0.0.dist-info/top_level.txt
zefactor-2.0.0.dist-info/RECORD
