Metadata-Version: 2.1
Name: zefactor
Version: 2.0.0
Summary: Flexible find and replace for refactoring projects.
Home-page: https://github.com/alexethier/zefactor
Author: Alex Ethier
Author-email: aethier@gmail.com
License: MIT
Classifier: Development Status :: 1 - Planning
Classifier: License :: OSI Approved :: BSD License
Classifier: Operating System :: POSIX :: Linux
Classifier: Programming Language :: Python :: 3
Classifier: Programming Language :: Python :: 3.4
Classifier: Programming Language :: Python :: 3.5
License-File: LICENSE
Requires-Dist: zind
Requires-Dist: zompt
